Polygen2D.py
Polygen2D-0.1.2.dist-info/LICENSE
Polygen2D-0.1.2.dist-info/METADATA
Polygen2D-0.1.2.dist-info/WHEEL
Polygen2D-0.1.2.dist-info/top_level.txt
Polygen2D-0.1.2.dist-info/RECORD
