Metadata-Version: 2.1
Name: Polygen2D
Version: 0.1.2
Summary: Polygen2D: Polygen in 2D with Python.
Home-page: https://github.com/Litlteor/Polygen2D
Author: Littleor
Author-email: admin@sixming.com
License: MIT
Platform: UNKNOWN
Classifier: License :: OSI Approved :: MIT License
Classifier: Programming Language :: Python
Classifier: Programming Language :: Python :: 3
Classifier: Programming Language :: Python :: 3.6
Classifier: Programming Language :: Python :: Implementation :: CPython
Classifier: Programming Language :: Python :: Implementation :: PyPy
Requires-Python: >=3.6.0
Requires-Dist: numpy
